MANIFEST.in
README.md
requirements.txt
setup.py
merkl/__init__.py
merkl/__main__.py
merkl/cache.py
merkl/dot.py
merkl/exceptions.py
merkl/future.py
merkl/io.py
merkl/logger.py
merkl/task.py
merkl/util_tasks.py
merkl/utils.py
merkl.egg-info/PKG-INFO
merkl.egg-info/SOURCES.txt
merkl.egg-info/dependency_links.txt
merkl.egg-info/entry_points.txt
merkl.egg-info/requires.txt
merkl.egg-info/top_level.txt
merkl/cli/__init__.py
merkl/cli/cache.py
merkl/cli/cli.py
merkl/cli/dot.py
merkl/cli/init.py
merkl/cli/migrate.py
merkl/cli/run.py
merkl/tests/__init__.py
merkl/tests/test_cache.py
merkl/tests/test_io.py
merkl/tests/test_task.py