Metadata-Version: 2.1
Name: merkl
Version: 0.5
Summary: MerkL
Home-page: https://github.com/martindbp/merkl
Author: Martin Pettersson
Author-email: me@martindbp.com
